bitcoin_p2p/__init__.py
bitcoin_p2p/p2p.py
bitcoin_p2p/tools.py
bitcoin_p2p-0.3.4.dist-info/LICENSE
bitcoin_p2p-0.3.4.dist-info/METADATA
bitcoin_p2p-0.3.4.dist-info/WHEEL
bitcoin_p2p-0.3.4.dist-info/top_level.txt
bitcoin_p2p-0.3.4.dist-info/RECORD
