Metadata-Version: 2.1
Name: bitcoin-p2p
Version: 0.3.4
Summary: Bitcoin p2p communication tools in python
Home-page: https://github.com/andreasgriffin/bitcoin-p2p
Author: Andreas Griffin
Author-email: andreasgriffin@proton.me
Classifier: Development Status :: 3 - Alpha
Classifier: Intended Audience :: Developers
Classifier: Programming Language :: Python
Classifier: Programming Language :: Python :: 3
Requires-Python: >=3.7,<4.0
License-File: LICENSE
Requires-Dist: prettytable (==3.3.0)
Requires-Dist: ptable (==0.9.2)
Requires-Dist: wcwidth (==0.2.6)
